extract_inner_function/__init__.py
extract_inner_function-0.0.1.dist-info/METADATA
extract_inner_function-0.0.1.dist-info/WHEEL
extract_inner_function-0.0.1.dist-info/licenses/LICENSE
extract_inner_function-0.0.1.dist-info/RECORD
