Metadata-Version: 2.3
Name: extract_inner_function
Version: 0.0.1
Summary: A simple package to extract inner functions from an outer function
Project-URL: Homepage, https://github.com/zlliu246/extract_inner_function
Project-URL: Issues, https://github.com/zlliu246/extract_inner_function/issues
Author-email: Liu Zuo Lin <zlliu246@gmail.com>
Classifier: License :: OSI Approved :: MIT License
Classifier: Operating System :: OS Independent
Classifier: Programming Language :: Python :: 3
Requires-Python: >=3.8
